py_data/__init__.py
py_data/py_data.py
py_data-0.0.5.dist-info/LICENSE
py_data-0.0.5.dist-info/METADATA
py_data-0.0.5.dist-info/WHEEL
py_data-0.0.5.dist-info/top_level.txt
py_data-0.0.5.dist-info/RECORD
